emeral/__init__.py
emeral/display.py
emeral/entity.py
emeral/events.py
emeral/image.py
emeral/resources/logo.png
emeral-0.8.5.dist-info/LICENSE
emeral-0.8.5.dist-info/METADATA
emeral-0.8.5.dist-info/WHEEL
emeral-0.8.5.dist-info/top_level.txt
emeral-0.8.5.dist-info/RECORD
