Metadata-Version: 2.1
Name: emeral
Version: 0.8.5
Summary: A library for making simple 2D games
Author: ga.ga.ga.ga.ga
Author-email: 1602422136@qq.com
License: MIT
Keywords: emeral
Classifier: License :: OSI Approved :: MIT License
Classifier: Programming Language :: Python :: 3
Classifier: Programming Language :: Python :: 3.7
Classifier: Programming Language :: Python :: 3.8
Classifier: Programming Language :: Python :: 3.9
Classifier: Programming Language :: Python :: 3.10
Requires-Python: >=3.7
License-File: LICENSE
Requires-Dist: pygame>=2.0.0
Requires-Dist: numpy>=1.20.0
Requires-Dist: pillow>=8.0.0
Requires-Dist: pywin32; sys_platform == "win32"
